<?xml version="1.0" encoding="utf-8"?>
<!--Generated by NHibernate.Mapping.Attributes on 2015-05-09 09:14:09Z.-->
<hibernate-mapping xmlns="urn:nhibernate-mapping-2.2">
  <class table="ocorrencias" name="TI_Lab_2015.Model.Ocorrencia, TI_Lab_2015">
    <id name="Id" column="id">
      <generator class="native" />
    </id>
    <property name="Conteudo" column="conteudo" />
    <property name="Inclusao" column="inclusao" />
    <property name="ocorrencia" column="ocorrencia" />
    <many-to-one name="Morador" column="id_morador" />
  </class>
</hibernate-mapping>